{
  "A": [],
  "B": ["0000000", "1111100", "1000010", "1000001", "1000001", "1000010", "1111100", "1000010", "1000001", "1000001", "1000010", "1111100", "0000000", "0000000"],
  "C": [],
  "D": [],
  "E": [],
  "F": [],
  "G": [],
  "H": [],
  "I": [],
  "J": [],
  "K": [],
  "L": [],
  "M": [],
  "N": [],
  "O": [],
  "P": [],
  "Q": [],
  "R": [],
  "S": [],
  "T": [],
  "U": [],
  "V": [],
  "W": [],
  "X": [],
  "Y": [],
  "Z": [],
  "a": [],
  "b": [],
  "c": [],
  "d": [],
  "e": [],
  "f": [],
  "g": [],
  "h": [],
  "i": [],
  "j": [],
  "k": [],
  "l": ["0", "1", "1", "1", "1", "1", "1", "1", "1", "1", "1", "1", "0", "0"], 
  "m": [],
  "n": [],
  "o": [],
  "p": [],
  "q": [],
  "r": [],
  "s": [],
  "t": [],
  "u": [],
  "v": [],
  "w": [],
  "x": [],
  "y": [],
  "z": []
}
